{
  "placeholderImages": [
    {
      "id": "profile-photo",
      "description": "Professional Headshot",
      "imageUrl": "https://picsum.photos/seed/prince/400/400",
      "imageHint": "man portrait"
    },
    {
      "id": "qiklet-thumbnail",
      "description": "Hyperlocal Marketplace Dashboard",
      "imageUrl": "https://picsum.photos/seed/qiklet/800/600",
      "imageHint": "ecommerce dashboard"
    },
    {
      "id": "iot-platform-thumbnail",
      "description": "IoT Device Monitoring Platform",
      "imageUrl": "https://picsum.photos/seed/iot/800/600",
      "imageHint": "iot telemetry"
    },
    {
      "id": "aws-opt-thumbnail",
      "description": "Cloud Infrastructure Optimization",
      "imageUrl": "https://picsum.photos/seed/aws/800/600",
      "imageHint": "cloud server"
    }
  ]
}